buble/__init__.py
buble/main.py
buble-6.0.dist-info/LICENSE
buble-6.0.dist-info/METADATA
buble-6.0.dist-info/WHEEL
buble-6.0.dist-info/top_level.txt
buble-6.0.dist-info/RECORD
